tofu/__init__.py
tofu/config.py
tofu/find_large_spots.py
tofu/genreco.py
tofu/gui.py
tofu/gui.ui
tofu/lamino.py
tofu/preprocess.py
tofu/reco.py
tofu/tasks.py
tofu/util.py
tofu/ez/RR_external.py
tofu/ez/__init__.py
tofu/ez/ctdir_walker.py
tofu/ez/evaluate_sharpness.py
tofu/ez/find_axis_cmd_gen.py
tofu/ez/image_read_write.py
tofu/ez/main.py
tofu/ez/main_nlm.py
tofu/ez/params.py
tofu/ez/tofu_cmd_gen.py
tofu/ez/ufo_cmd_gen.py
tofu/ez/util.py
tofu/ez/yaml_in_out.py
tofu/ez/GUI/__init__.py
tofu/ez/GUI/default_settings.yaml
tofu/ez/GUI/ezufo_launcher.py
tofu/ez/GUI/image_viewer.py
tofu/ez/GUI/login_dialog.py
tofu/ez/GUI/message_dialog.py
tofu/ez/GUI/Advanced/__init__.py
tofu/ez/GUI/Advanced/advanced.py
tofu/ez/GUI/Advanced/ffc.py
tofu/ez/GUI/Advanced/nlmdn.py
tofu/ez/GUI/Advanced/optimization.py
tofu/ez/GUI/Main/__init__.py
tofu/ez/GUI/Main/centre_of_rotation.py
tofu/ez/GUI/Main/config.py
tofu/ez/GUI/Main/filters.py
tofu/ez/GUI/Main/phase_retrieval.py
tofu/ez/GUI/Main/region_and_histogram.py
tofu/ez/GUI/Stitch_tools_tab/__init__.py
tofu/ez/GUI/Stitch_tools_tab/ez_360_multi_stitch_qt.py
tofu/ez/GUI/Stitch_tools_tab/ez_360_overlap_qt.py
tofu/ez/GUI/Stitch_tools_tab/ezmview_qt.py
tofu/ez/GUI/Stitch_tools_tab/ezstitch_qt.py
tofu/ez/Helpers/__init__.py
tofu/ez/Helpers/find_360_overlap.py
tofu/ez/Helpers/mview_main.py
tofu/ez/Helpers/stitch_funcs.py
tofu/flow/__init__.py
tofu/flow/config.json
tofu/flow/execution.py
tofu/flow/filedirdialog.py
tofu/flow/main.py
tofu/flow/models.py
tofu/flow/propertylinksmodels.py
tofu/flow/propertylinkswidget.py
tofu/flow/runslider.py
tofu/flow/scene.py
tofu/flow/util.py
tofu/flow/viewer.py
tofu/flow/composites/ffc-links.cm
tofu/flow/composites/pr.cm
tofu/tests/__init__.py
tofu/tests/conftest.py
tofu/tests/flow_util.py
tofu/tests/test_flow_execution.py
tofu/tests/test_flow_main.py
tofu/tests/test_flow_models.py
tofu/tests/test_flow_propertylinksmodels.py
tofu/tests/test_flow_propertylinkswidget.py
tofu/tests/test_flow_runslider.py
ufo_tofu-0.12.0.dist-info/LICENSE
ufo_tofu-0.12.0.dist-info/METADATA
ufo_tofu-0.12.0.dist-info/WHEEL
ufo_tofu-0.12.0.dist-info/top_level.txt
ufo_tofu-0.12.0.dist-info/RECORD
