Metadata-Version: 2.1
Name: ufo-tofu
Version: 0.12.0
Summary: A fast, versatile and user-friendly image processing toolkit for computed tomography
Home-page: http://github.com/ufo-kit/tofu
Author: Matthias Vogelgesang
Author-email: matthias.vogelgesang@kit.edu
License: LGPL
Platform: UNKNOWN
Requires-Python: >=3
Requires-Dist: PyGObject
Requires-Dist: PyQt5
Requires-Dist: imageio
Requires-Dist: networkx
Requires-Dist: numpy
Requires-Dist: pyqtconsole
Requires-Dist: qtpynodeeditor
Requires-Dist: xdg
